starslayer/__init__.py
starslayer/color_profiles.txt
starslayer/consts.py
starslayer/files.py
starslayer/game_controls.py
starslayer/game_state.py
starslayer/gamelib.py
starslayer/graphics.py
starslayer/keys.txt
starslayer/main.py
starslayer/objects.py
starslayer/levels/level_1.txt
starslayer/sprites/player/star_player.gif
starslayer/sprites/player/star_player_damaged.gif
star_slayer-0.0.10a0.dist-info/METADATA
star_slayer-0.0.10a0.dist-info/WHEEL
star_slayer-0.0.10a0.dist-info/top_level.txt
star_slayer-0.0.10a0.dist-info/RECORD
