Metadata-Version: 2.1
Name: star-slayer
Version: 0.0.10a0
Summary: Little game made with Gamelib
Home-page: https://github.com/NLGS2907/star-slayer
Author: NLGS
Author-email: flighterman@fi.uba.ar
License: MIT
Platform: UNKNOWN
Classifier: Development Status :: 3 - Alpha
Classifier: License :: OSI Approved :: MIT License
Classifier: Programming Language :: Python :: 3.10
